MANIFEST.in
README.txt
setup.cfg
setup.py
XStatic_JosefinSans.egg-info/PKG-INFO
XStatic_JosefinSans.egg-info/SOURCES.txt
XStatic_JosefinSans.egg-info/dependency_links.txt
XStatic_JosefinSans.egg-info/namespace_packages.txt
XStatic_JosefinSans.egg-info/not-zip-safe
XStatic_JosefinSans.egg-info/top_level.txt
xstatic/__init__.py
xstatic/pkg/__init__.py
xstatic/pkg/josefinsans/__init__.py
xstatic/pkg/josefinsans/data/fonts/Bold/JosefinSans-Bold.eot
xstatic/pkg/josefinsans/data/fonts/Bold/JosefinSans-Bold.svg
xstatic/pkg/josefinsans/data/fonts/Bold/JosefinSans-Bold.ttf
xstatic/pkg/josefinsans/data/fonts/Bold/JosefinSans-Bold.woff
xstatic/pkg/josefinsans/data/fonts/Bold/JosefinSans-Bold.woff2
xstatic/pkg/josefinsans/data/fonts/BoldItalic/JosefinSans-BoldItalic.eot
xstatic/pkg/josefinsans/data/fonts/BoldItalic/JosefinSans-BoldItalic.svg
xstatic/pkg/josefinsans/data/fonts/BoldItalic/JosefinSans-BoldItalic.ttf
xstatic/pkg/josefinsans/data/fonts/BoldItalic/JosefinSans-BoldItalic.woff
xstatic/pkg/josefinsans/data/fonts/BoldItalic/JosefinSans-BoldItalic.woff2
xstatic/pkg/josefinsans/data/fonts/Italic/JosefinSans-Italic.eot
xstatic/pkg/josefinsans/data/fonts/Italic/JosefinSans-Italic.svg
xstatic/pkg/josefinsans/data/fonts/Italic/JosefinSans-Italic.ttf
xstatic/pkg/josefinsans/data/fonts/Italic/JosefinSans-Italic.woff
xstatic/pkg/josefinsans/data/fonts/Italic/JosefinSans-Italic.woff2
xstatic/pkg/josefinsans/data/fonts/Light/JosefinSans-Light.eot
xstatic/pkg/josefinsans/data/fonts/Light/JosefinSans-Light.otf
xstatic/pkg/josefinsans/data/fonts/Light/JosefinSans-Light.svg
xstatic/pkg/josefinsans/data/fonts/Light/JosefinSans-Light.ttf
xstatic/pkg/josefinsans/data/fonts/Light/JosefinSans-Light.woff
xstatic/pkg/josefinsans/data/fonts/Light/JosefinSans-Light.woff2
xstatic/pkg/josefinsans/data/fonts/LightItalic/JosefinSans-LightItalic.eot
xstatic/pkg/josefinsans/data/fonts/LightItalic/JosefinSans-LightItalic.otf
xstatic/pkg/josefinsans/data/fonts/LightItalic/JosefinSans-LightItalic.svg
xstatic/pkg/josefinsans/data/fonts/LightItalic/JosefinSans-LightItalic.ttf
xstatic/pkg/josefinsans/data/fonts/LightItalic/JosefinSans-LightItalic.woff
xstatic/pkg/josefinsans/data/fonts/LightItalic/JosefinSans-LightItalic.woff2
