Metadata-Version: 1.0
Name: XStatic-JosefinSans
Version: 0.0.0
Summary: JosefinSans 0.0 (XStatic packaging standard)
Home-page: https://www.fontsquirrel.com/fonts/Josefin-Sans
Author: Serghei Mihai
Author-email: smihai@entrouvert.com
License: (same as JosefinSans)
Keywords: josefinsans xstatic
Platform: any
